floras-0.1.0.dist-info/METADATA
floras-0.1.0.dist-info/WHEEL
floras-0.1.0.dist-info/entry_points.txt
floras-0.1.0.dist-info/licenses/LICENSE.txt
floras/__init__.py
floras/__version__.py
floras/components/__init__.py
floras/components/automata.py
floras/components/grid.py
floras/components/plotting.py
floras/components/product.py
floras/components/transition_system.py
floras/components/utils.py
floras/main.py
floras/optimization/__init__.py
floras/optimization/optimization.py
floras/optimization/optimize.py
floras/optimization/setup_graphs.py
floras/optimization/utils.py
floras/simulation/agents.py
floras/simulation/animation.py
floras/simulation/game.py
floras/simulation/utils.py
floras-0.1.0.dist-info/RECORD
