Metadata-Version: 2.1
Name: floras
Version: 0.1.0
Summary: A package for network flow-based test synthesis.
Keywords: test synthesis,network flow,testing
Author-Email: floras developers <tulip@tulip-control.org>
License: BSD-3-Clause
Classifier: License :: OSI Approved :: BSD License
Classifier: Development Status :: 2 - Pre-Alpha
Classifier: Intended Audience :: Science/Research
Classifier: Topic :: Scientific/Engineering
Classifier: Operating System :: OS Independent
Classifier: Programming Language :: Python
Classifier: Programming Language :: Python :: 3 :: Only
Project-URL: Homepage, https://github.com/tulip-control/floras
Project-URL: Bug Tracker, https://github.com/tulip-control/floras/issues
Project-URL: Documentation, https://floras.sourceforge.io/
Project-URL: Source Code, https://github.com/tulip-control/floras
Requires-Python: <3.13,>=3.10
Requires-Dist: numpy>=1.24.1
Requires-Dist: gurobipy==11.0.3
Requires-Dist: imageio>=2.19.3
Requires-Dist: ipdb>=0.13.11
Requires-Dist: matplotlib>=3.9.2
Requires-Dist: networkx>=3.0
Requires-Dist: scipy>=1.10.1
Requires-Dist: tulip==1.4.0
Requires-Dist: pygraphviz>=1.13
Requires-Dist: jupyter>=1.1.1
Provides-Extra: docs
Requires-Dist: mkdocs>=1.6.1; extra == "docs"
Requires-Dist: mkdocs-material>=9.5.34; extra == "docs"
Requires-Dist: mkdocstrings-python>=1.11.1; extra == "docs"
Requires-Dist: mkdocs-jupyter>=0.25.1; extra == "docs"
Provides-Extra: tests
Requires-Dist: pytest>=8.3.3; extra == "tests"
Requires-Dist: coverage>=7.6.1; extra == "tests"
